{
  "sample_id": "fb707964c2374c3b",
  "source_capture": "C:\\Users\\Crowsoda\\CodingProjects\\g20_demo/data/captures\\MAN_26012026_193636_825MHz.rfcap",
  "time_offset_sec": 16.100764346914872,
  "duration_sec": 0.012204894285893886,
  "window_start_sec": 16.056866794057818,
  "window_duration_sec": 0.10000000000000142,
  "center_freq_mhz": 825.1409553641347,
  "center_freq_hz": 825140955.3641347,
  "sample_rate_mhz": 5.0,
  "sample_rate": 5000000.0,
  "created_at": "2026-01-26T19:47:44.352797Z",
  "created_by": "user_label",
  "coordinate_format": "real_units",
  "spectrogram_params": {
    "fft_size": 4096,
    "hop_length": 2048,
    "dynamic_range_db": 80.0,
    "output_size": [
      1024,
      1024
    ]
  },
  "boxes": [
    {
      "x_min": 449,
      "x_max": 574,
      "y_min": 697,
      "y_max": 714,
      "label": "signal",
      "confidence": null
    }
  ],
  "original_boxes": [
    {
      "time_start_sec": 16.100764346914872,
      "time_end_sec": 16.112969241200766,
      "freq_start_mhz": 826.6538058314244,
      "freq_end_mhz": 826.735581532359
    }
  ]
}